LICENSE
MANIFEST.in
README.rst
setup.py
django_dublincore.egg-info/PKG-INFO
django_dublincore.egg-info/SOURCES.txt
django_dublincore.egg-info/dependency_links.txt
django_dublincore.egg-info/top_level.txt
dublincore/__init__.py
dublincore/admin.py
dublincore/models.py