Metadata-Version: 1.1
Name: django-dublincore
Version: 0.1
Summary: A simple Django app to attach Dublin Core metadata to arbitrary Django objects
Home-page: https://github.com/mredar/django-dublincore
Author: Mark Redar
Author-email: mredar@gmail.com
License: BSD License - see LICENSE file
Platform: UNKNOWN
Classifier: Development Status :: 4 - Beta
Classifier: Environment :: Web Environment
Classifier: Framework :: Django
Classifier: Intended Audience :: Developers
Classifier: License :: OSI Approved :: BSD License
Classifier: Operating System :: OS Independent
Classifier: Programming Language :: Python
Classifier: Programming Language :: Python :: 2.6
Classifier: Programming Language :: Python :: 2.7
Classifier: Topic :: Internet :: WWW/HTTP
Classifier: Topic :: Internet :: WWW/HTTP :: Dynamic Content
